service_flow/__init__.py
service_flow/exceptions.py
service_flow/flow.py
service_flow/fork.py
service_flow/middleware.py
service_flow/timer.py
service_flow-0.3.1.dist-info/LICENSE
service_flow-0.3.1.dist-info/METADATA
service_flow-0.3.1.dist-info/WHEEL
service_flow-0.3.1.dist-info/top_level.txt
service_flow-0.3.1.dist-info/RECORD
