Metadata-Version: 2.1
Name: service-flow
Version: 0.3.1
Summary: service object flow orchestrator
Home-page: https://github.com/jackxxu/service_flow
Author: Xiaosong Xu
Author-email: jackxxu@gmail.com
Project-URL: Bug Tracker, https://github.com/jackxxu/service_flow/issues
Classifier: Programming Language :: Python :: 3
Classifier: License :: OSI Approved :: MIT License
Classifier: Operating System :: OS Independent
Requires-Python: >=3.6
License-File: LICENSE
